connect_n_3d/__init__.py
connect_n_3d/agents.py
connect_n_3d/board.py
connect_n_3d/env.py
connect_n_3d-0.0.3.dist-info/licenses/LICENSE
connect_n_3d-0.0.3.dist-info/METADATA
connect_n_3d-0.0.3.dist-info/WHEEL
connect_n_3d-0.0.3.dist-info/top_level.txt
connect_n_3d-0.0.3.dist-info/RECORD
